README.txt
setup.py
easyaws/__init__.py
easyaws/easyaws
easyaws/ec2list
easyaws/ec2ssh
easyaws.egg-info/PKG-INFO
easyaws.egg-info/SOURCES.txt
easyaws.egg-info/dependency_links.txt
easyaws.egg-info/not-zip-safe
easyaws.egg-info/requires.txt
easyaws.egg-info/top_level.txt