Metadata-Version: 1.1
Name: easyaws
Version: 0.0.3
Summary: Easy to use AWS commands for developers (currently supports EC2; tools for S3 coming soon)
Home-page: http://github.com/amberj/easyaws
Author: Amber Jain
Author-email: i.amber.jain@gmail.com
License: ISC
Keywords: amazon,aws,ec2,ami,ssh,cloud,boto,easy,tools,tool,cli,command,devs,developers
Platform: UNKNOWN
Classifier: Intended Audience :: Developers
Classifier: Natural Language :: English
Classifier: Environment :: Console
Classifier: Topic :: Utilities
